receipt_parser_core/__init__.py
receipt_parser_core/config.py
receipt_parser_core/enhancer.py
receipt_parser_core/objectview.py
receipt_parser_core/parse.py
receipt_parser_core/receipt.py
receipt_parser_core/util.py
receipt_parser_core-0.2.5.dist-info/entry_points.txt
receipt_parser_core-0.2.5.dist-info/LICENSE
receipt_parser_core-0.2.5.dist-info/WHEEL
receipt_parser_core-0.2.5.dist-info/METADATA
receipt_parser_core-0.2.5.dist-info/RECORD
