Metadata-Version: 2.1
Name: receipt-parser-core
Version: 0.2.5
Summary: A supermarket receipt parser written in Python using tesseract OCR
Home-page: https://github.com/ReceiptManager/receipt-parser-legacy
License: Apache-2.0
Keywords: receipt,ocr,parser
Author: Matthias Endler
Author-email: matthias-endler@gmx.net
Requires-Python: >=3.7,<3.8
Classifier: License :: OSI Approved :: Apache Software License
Classifier: Programming Language :: Python :: 3
Classifier: Programming Language :: Python :: 3.7
Requires-Dist: Pillow (>=8.1.2,<9.0.0)
Requires-Dist: numpy (>=1.19.4,<2.0.0)
Requires-Dist: opencv-python (>=4.4.0,<5.0.0)
Requires-Dist: py (>=1.10.0,<2.0.0)
Requires-Dist: pytesseract (>=0.3.6,<0.4.0)
Requires-Dist: python-dateutil (>=2.8.1,<3.0.0)
Requires-Dist: pyyaml (>=5.3.1,<6.0.0)
Requires-Dist: scipy (>=1.6.2,<2.0.0)
Requires-Dist: terminaltables (>=3.1.0,<4.0.0)
Requires-Dist: wand (>=0.6.3,<0.7.0)
Project-URL: Repository, https://github.com/ReceiptManager/receipt-parser-legacy
